segmate/__init__.py
segmate/dataset.py
segmate/object_detector.py
segmate/segmenter.py
segmate/utils.py
segmate-0.3.1.dist-info/METADATA
segmate-0.3.1.dist-info/WHEEL
segmate-0.3.1.dist-info/licenses/LICENSE
segmate-0.3.1.dist-info/RECORD
