Metadata-Version: 2.1
Name: segmate
Version: 0.3.1
Summary: SegMate package
Project-URL: Homepage, https://github.com/VectorInstitute/SegMate
Project-URL: Bug Tracker, https://github.com/VectorInstitute/SegMate/issues
Author-email: Marshall Wang <marshall.wang@vectorinstitute.ai>, Vahid Reza Khazaie <vahidreza.khazaie@vectorinstitute.ai>
License-File: LICENSE
Classifier: License :: OSI Approved :: BSD License
Classifier: Operating System :: OS Independent
Classifier: Programming Language :: Python :: 3
Requires-Python: >=3.9
Requires-Dist: datasets>=2.13.0
Requires-Dist: groundingdino
Requires-Dist: huggingface-hub
Requires-Dist: matplotlib
Requires-Dist: numpy>=1.22.4
Requires-Dist: opencv-python>=4.7.0
Requires-Dist: pycocotools
Requires-Dist: segment-anything
Requires-Dist: torch>=2.0.1
Requires-Dist: tqdm>=4.62.3
